paper_secret/__init__.py
paper_secret/depaper.py
paper_secret/enpaper.py
paper_secret/util.py
paper_secret-0.1.3.dist-info/LICENSE
paper_secret-0.1.3.dist-info/METADATA
paper_secret-0.1.3.dist-info/WHEEL
paper_secret-0.1.3.dist-info/entry_points.txt
paper_secret-0.1.3.dist-info/top_level.txt
paper_secret-0.1.3.dist-info/RECORD
