Metadata-Version: 2.1
Name: paper-secret
Version: 0.1.3
Summary: Shamir Secret Sharing on paper using gfshare
Home-page: https://codeberg.org/privacy1st/paper-secret
Author: Daniel Langbein
Author-email: daniel@systemli.org
Project-URL: Bug Tracker, https://codeberg.org/privacy1st/paper-secret/issues
Classifier: Development Status :: 4 - Beta
Classifier: Programming Language :: Python :: 3
Classifier: License :: CC0 1.0 Universal (CC0 1.0) Public Domain Dedication
Classifier: Operating System :: Unix
Requires-Python: >=3.10
License-File: LICENSE
